exesexe.py
exesexe-1.0.0.dist-info/DESCRIPTION.rst
exesexe-1.0.0.dist-info/METADATA
exesexe-1.0.0.dist-info/RECORD
exesexe-1.0.0.dist-info/WHEEL
exesexe-1.0.0.dist-info/entry_points.txt
exesexe-1.0.0.dist-info/metadata.json
exesexe-1.0.0.dist-info/top_level.txt
