Metadata-Version: 2.0
Name: exesexe
Version: 1.0.0
Summary: Manipulate return codes from executables
Home-page: https://github.com/mtkennerly/exesexe
Author: Matthew T. Kennerly (mtkennerly)
Author-email: mtkennerly@gmail.com
License: MIT
Keywords: return code
Platform: UNKNOWN
Classifier: Development Status :: 5 - Production/Stable
Classifier: Intended Audience :: End Users/Desktop
Classifier: License :: OSI Approved :: MIT License
Classifier: Natural Language :: English
Classifier: Programming Language :: Python
Classifier: Programming Language :: Python :: 2.7
Classifier: Programming Language :: Python :: 3
Classifier: Topic :: Utilities
Provides-Extra: dev
Requires-Dist: invoke; extra == 'dev'
Requires-Dist: pyinstaller; extra == 'dev'
Requires-Dist: tox; extra == 'dev'
